LICENSE
MANIFEST.in
README.rst
setup.py
stockpile/__about__.py
stockpile/__init__.py
stockpile/base.py
stockpile/exceptions.py
stockpile/filesystem.py
stockpile/hashed.py
stockpile/s3.py
stockpile.egg-info/PKG-INFO
stockpile.egg-info/SOURCES.txt
stockpile.egg-info/dependency_links.txt
stockpile.egg-info/not-zip-safe
stockpile.egg-info/requires.txt
stockpile.egg-info/top_level.txt
stockpile/utils/__init__.py
stockpile/utils/_os.py
stockpile/utils/encoding.py
stockpile/utils/locks.py