Metadata-Version: 1.1
Name: stockpile
Version: 0.1
Summary: Generic file storage abstraction
Home-page: https://github.com/dstufft/stockpile/
Author: Donald Stufft
Author-email: donald.stufft@gmail.com
License: Simplified BSD
Platform: UNKNOWN
Classifier: License :: OSI Approved :: BSD License
Classifier: Operating System :: POSIX
Classifier: Programming Language :: Python :: 2.7
Classifier: Programming Language :: Python :: Implementation :: CPython
Classifier: Programming Language :: Python :: Implementation :: PyPy
